{
  "attempt_id": "20260616T015708-6a9c53e3",
  "bead_id": "ddx-6ae5134b",
  "trigger": "context canceled",
  "scanned_at": "2026-06-16T02:07:28.852806375Z",
  "reaped": [
    {
      "pid": 1280129,
      "provider": "codex",
      "command": "/home/linuxbrew/.linuxbrew/bin/codex --no-alt-screen",
      "age_seconds": 0,
      "action": "terminated",
      "reason": "running_phase_non_route_provider_child"
    },
    {
      "pid": 1280203,
      "provider": "gemini",
      "command": "node /home/erik/.local/share/mise/installs/node/22.21.1/bin/gemini",
      "age_seconds": 0,
      "action": "terminated",
      "reason": "running_phase_non_route_provider_child"
    }
  ]
}